dsmate/__init__.py
dsmate/load.py
dsmate/model.py
dsmate/preprocess.py
dsmate-0.0.8.dist-info/LICENSE.txt
dsmate-0.0.8.dist-info/METADATA
dsmate-0.0.8.dist-info/WHEEL
dsmate-0.0.8.dist-info/top_level.txt
dsmate-0.0.8.dist-info/RECORD
