Metadata-Version: 2.1
Name: dsmate
Version: 0.0.8
Summary: Simplify data tasks in Python with interactive interface for effortless data interaction. Empower your data journey today.
Home-page: https://github.com/DL4150/dsmate
Author: Daniel Lawrence
Author-email: daniellawrence4150@gmail.com
License: MIT
Keywords: python,data science,data analytics,machine learning,data,analysis
Classifier: Development Status :: 3 - Alpha
Classifier: Intended Audience :: Science/Research
Classifier: Intended Audience :: Education
Classifier: License :: OSI Approved :: MIT License
Classifier: Programming Language :: Python :: 3
License-File: LICENSE.txt
Requires-Dist: pandas
Requires-Dist: sklearn
Requires-Dist: scipy
Requires-Dist: matplotlib
Requires-Dist: seaborn
Requires-Dist: numpy
